ParametricSpectralClustering/__init__.py
ParametricSpectralClustering/psc.py
ParametricSpectralClustering-0.0.5.data/scripts/clustering.py
ParametricSpectralClustering-0.0.5.data/scripts/run.py
ParametricSpectralClustering-0.0.5.data/scripts/train_psc.py
ParametricSpectralClustering-0.0.5.dist-info/LICENSE.txt
ParametricSpectralClustering-0.0.5.dist-info/METADATA
ParametricSpectralClustering-0.0.5.dist-info/WHEEL
ParametricSpectralClustering-0.0.5.dist-info/top_level.txt
ParametricSpectralClustering-0.0.5.dist-info/RECORD
