Metadata-Version: 2.2
Name: ParametricSpectralClustering
Version: 0.0.5
Summary: A library for users to use parametric spectral clustering
Home-page: 
Author: Ivy Chang, Hsin Ju Tai
Author-email: ivy900403@gmail.com, luludai020127@gmail.com
License: MIT
Keywords: Spectral Clustering,Incremental Clustering,Online Clustering,Non-linear clustering
Classifier: Development Status :: 3 - Alpha
Classifier: License :: OSI Approved :: MIT License
Classifier: Programming Language :: Python :: 3.10
Classifier: Topic :: Scientific/Engineering :: Artificial Intelligence
Classifier: Operating System :: OS Independent
Requires-Python: >=3.8
License-File: LICENSE.txt
Requires-Dist: scipy>=1.13.0
Requires-Dist: torch>=2.2.2
Requires-Dist: torchaudio>=2.2.2
Requires-Dist: torchvision>=0.17.2
Requires-Dist: scikit-learn>=1.4.2
Requires-Dist: pandas>=2.2.2
Requires-Dist: numpy==1.26.4
Requires-Dist: matplotlib>=3.8.4
Dynamic: author
Dynamic: author-email
Dynamic: classifier
Dynamic: description
Dynamic: description-content-type
Dynamic: keywords
Dynamic: license
Dynamic: requires-dist
Dynamic: requires-python
Dynamic: summary
